{
    "DailyEventGoToFinishByRedDot": {
        "recognition": {
            "param": {
                // 注意避免x轴<0越界
                "roi_offset": [
                    -50,
                    -50,
                    20,
                    100
                ]
            }
        }
    },
    "DailyEventGoToFinishByNew": {
        "recognition": {
            "param": {
                // 注意避免x轴<0越界
                "roi_offset": [
                    -50,
                    -50,
                    20,
                    100
                ]
            }
        }
    },
    "DailyEventRecognitionRedDot": {
        "recognition": {
            "param": {
                "roi": [
                    190,
                    102,
                    104,
                    583
                ]
            }
        }
    },
    "DailyEventRecognitionNewColor": {
        "recognition": {
            "param": {
                "roi": [
                    190,
                    102,
                    104,
                    583
                ]
            }
        }
    },
    "DailyEventRecognitionItemTextByRedDot": {
        "recognition": {
            "param": {
                "roi_offset": [
                    -214,
                    -2,
                    202,
                    59
                ]
            }
        }
    },
    "DailyEventRecognitionItemTextByNew": {
        "recognition": {
            "param": {
                "roi_offset": [
                    -214,
                    -2,
                    202,
                    59
                ]
            }
        }
    }
}
